LICENSE.txt
MANIFEST.in
README.rst
setup.cfg
setup.py
typogrify/__init__.py
typogrify/filters.py
typogrify.egg-info/PKG-INFO
typogrify.egg-info/SOURCES.txt
typogrify.egg-info/dependency_links.txt
typogrify.egg-info/requires.txt
typogrify.egg-info/top_level.txt
typogrify/templatetags/__init__.py
typogrify/templatetags/jinja_filters.py
typogrify/templatetags/typogrify_tags.py