Metadata-Version: 1.1
Name: typogrify
Version: 2.0.1
Summary: Filters to enhance web typography, including support for Django & Jinja templates
Home-page: https://github.com/mintchaos/typogrify
Author: Christian Metts, Justin Mayer, Chris Drackett
Author-email: entroP@gmail.com
License: BSD
Platform: UNKNOWN
Classifier: Development Status :: 5 - Production/Stable
Classifier: Environment :: Web Environment
Classifier: Intended Audience :: Developers
Classifier: License :: OSI Approved :: BSD License
Classifier: Operating System :: OS Independent
Classifier: Programming Language :: Python
Classifier: Framework :: Django
Classifier: Framework :: Flask
Classifier: Topic :: Utilities
